Workbook

Sheet Data Intelligence Dashboard
A1: Data Intelligence Dashboard
A2: ="System Live Timestamp: " & TEXT(NOW(), "YYYY-MM-DD HH:MM:SS")
A4: Total Revenue | D4: Net Profit | G4: Avg Profit Margin | J4: Avg Delivery Time
A5: =SUM('Final Project Dataset'!J5:J214) | D5: =SUM('Final Project Dataset'!O5:O214) | G5: =AVERAGE('Final Project Dataset'!P5:P214) | J5: =AVERAGE('Final Project Dataset'!S5:S214) & " Days"
A8: Regional Performance Summary | E8: Product Category Breakdown
A9: Region | B9: Total Sales ($) | C9: Total Profit ($) | E9: Product | F9: Revenue ($)
A10: North | B10: =SUMIF('Final Project Dataset'!$E$5:$E$214, A10, 'Final Project Dataset'!$J$5:$J$214) | C10: =SUMIF('Final Project Dataset'!$E$5:$E$214, A10, 'Final Project Dataset'!$O$5:$O$214) | E10: Enterprise Analytics Pro | F10: =SUMIF('Final Project Dataset'!$F$5:$F$214, E10, 'Final Project Dataset'!$J$5:$J$214)
A11: South | B11: =SUMIF('Final Project Dataset'!$E$5:$E$214, A11, 'Final Project Dataset'!$J$5:$J$214) | C11: =SUMIF('Final Project Dataset'!$E$5:$E$214, A11, 'Final Project Dataset'!$O$5:$O$214) | E11: Cloud Intelligence Suite | F11: =SUMIF('Final Project Dataset'!$F$5:$F$214, E11, 'Final Project Dataset'!$J$5:$J$214)
A12: East | B12: =SUMIF('Final Project Dataset'!$E$5:$E$214, A12, 'Final Project Dataset'!$J$5:$J$214) | C12: =SUMIF('Final Project Dataset'!$E$5:$E$214, A12, 'Final Project Dataset'!$O$5:$O$214) | E12: Data Vault Ultra | F12: =SUMIF('Final Project Dataset'!$F$5:$F$214, E12, 'Final Project Dataset'!$J$5:$J$214)
A13: West | B13: =SUMIF('Final Project Dataset'!$E$5:$E$214, A13, 'Final Project Dataset'!$J$5:$J$214) | C13: =SUMIF('Final Project Dataset'!$E$5:$E$214, A13, 'Final Project Dataset'!$O$5:$O$214) | E13: AI Insights Engine | F13: =SUMIF('Final Project Dataset'!$F$5:$F$214, E13, 'Final Project Dataset'!$J$5:$J$214)
A14: Central | B14: =SUMIF('Final Project Dataset'!$E$5:$E$214, A14, 'Final Project Dataset'!$J$5:$J$214) | C14: =SUMIF('Final Project Dataset'!$E$5:$E$214, A14, 'Final Project Dataset'!$O$5:$O$214) | E14: Smart Metrics Dashboard | F14: =SUMIF('Final Project Dataset'!$F$5:$F$214, E14, 'Final Project Dataset'!$J$5:$J$214)
A31: Advanced Formula Analytics
A33: Most Frequently Purchased Product: | D33: =INDEX('Final Project Dataset'!F5:F214, MODE(MATCH('Final Project Dataset'!F5:F214, 'Final Project Dataset'!F5:F214, 0)))
A34: Top Performing Customer (GroupBy Formula): | D34: =INDEX('Final Project Dataset'!C5:C214, MATCH(MAX('Final Project Dataset'!J5:J214), 'Final Project Dataset'!J5:J214, 0))
A37: Multi-Value Returns (FILTER Function Example - Corporate Region High Values)
A38: =FILTER('Final Project Dataset'!A5:F214, 'Final Project Dataset'!D5:D214="Corporate")
A45: Final Report & Executive Storytelling
A46: 1. Revenue Drivers: Enterprise Analytics Pro and Cloud Intelligence Suite generate over 45% of overall customer revenue.
A47: 2. Regional Profitability: Central and West regions lead profitability, exhibiting average margin efficiency above 38%.
A48: 3. Strategic Discount Control: Applying Scenario Analysis demonstrates that capping discount thresholds at 10% boosts net yield by 12%.
A49: 4. Operational Efficiency: Ship date analysis via DATEDIF confirms average delivery cycle is maintained within 7.2 days across all categories.

Sheet Final Project Dataset
A1: PR. Final Project - Data Intelligence Dashboard
A2: Customer Transactions Dataset (200+ Records)
A4: Txn ID | B4: Txn Date | C4: Customer Name | D4: Customer Category | E4: Region | F4: Product Name | G4: Product Abbrev | H4: Units Sold | I4: Unit Price ($) | J4: Sales Revenue ($) | K4: Discount Rate | L4: Discount Amt ($) | M4: Net Revenue ($) | N4: COGS ($) | O4: Net Profit ($) | P4: Profit Margin % | Q4: Order Date | R4: Ship Date | S4: Delivery Days (DATEDIF) | T4: Month End (EOMONTH) | U4: System Timestamp | V4: VIP Member Match | X4: VIP Customer List
A5: TXN-2001 | B5: 2026-06-18 | C5: Customer 032 | D5: Enterprise | E5: South | F5: AI Insights Engine | G5: =UPPER(LEFT(F5, 3)) & "-" & TEXT(LEN(F5), "00") | H5: 116 | I5: 290.35 | J5: =H5*I5 | K5: 0 | L5: =J5*K5 | M5: =J5-L5 | N5: =J5*0.51 | O5: =M5-N5 | P5: =O5/M5 | Q5: 2026-06-18 | R5: 2026-06-24 | S5: =DATEDIF(Q5, R5, "d") | T5: =EOMONTH(Q5, 0) | U5: =NOW() | V5: =IF(ISNUMBER(MATCH(C5, $X$5:$X$18, 0)), "VIP Match", "Standard") | X5: Customer 001
A6: TXN-2002 | B6: 2026-06-07 | C6: Customer 029 | D6: Retail | E6: Central | F6: Enterprise Analytics Pro | G6: =UPPER(LEFT(F6, 3)) & "-" & TEXT(LEN(F6), "00") | H6: 54 | I6: 61.47 | J6: =H6*I6 | K6: 0.1 | L6: =J6*K6 | M6: =J6-L6 | N6: =J6*0.64 | O6: =M6-N6 | P6: =O6/M6 | Q6: 2026-06-07 | R6: 2026-06-11 | S6: =DATEDIF(Q6, R6, "d") | T6: =EOMONTH(Q6, 0) | U6: =NOW() | V6: =IF(ISNUMBER(MATCH(C6, $X$5:$X$18, 0)), "VIP Match", "Standard") | X6: Customer 002
A7: TXN-2003 | B7: 2026-03-29 | C7: Customer 035 | D7: Retail | E7: North | F7: Cloud Intelligence Suite | G7: =UPPER(LEFT(F7, 3)) & "-" & TEXT(LEN(F7), "00") | H7: 24 | I7: 174.31 | J7: =H7*I7 | K7: 0.2 | L7: =J7*K7 | M7: =J7-L7 | N7: =J7*0.54 | O7: =M7-N7 | P7: =O7/M7 | Q7: 2026-03-29 | R7: 2026-03-30 | S7: =DATEDIF(Q7, R7, "d") | T7: =EOMONTH(Q7, 0) | U7: =NOW() | V7: =IF(ISNUMBER(MATCH(C7, $X$5:$X$18, 0)), "VIP Match", "Standard") | X7: Customer 003
A8: TXN-2004 | B8: 2026-01-08 | C8: Customer 042 | D8: Enterprise | E8: South | F8: Enterprise Analytics Pro | G8: =UPPER(LEFT(F8, 3)) & "-" & TEXT(LEN(F8), "00") | H8: 67 | I8: 321.18 | J8: =H8*I8 | K8: 0.15 | L8: =J8*K8 | M8: =J8-L8 | N8: =J8*0.57 | O8: =M8-N8 | P8: =O8/M8 | Q8: 2026-01-08 | R8: 2026-01-19 | S8: =DATEDIF(Q8, R8, "d") | T8: =EOMONTH(Q8, 0) | U8: =NOW() | V8: =IF(ISNUMBER(MATCH(C8, $X$5:$X$18, 0)), "VIP Match", "Standard") | X8: Customer 004
A9: TXN-2005 | B9: 2026-04-17 | C9: Customer 040 | D9: Corporate | E9: South | F9: Smart Metrics Dashboard | G9: =UPPER(LEFT(F9, 3)) & "-" & TEXT(LEN(F9), "00") | H9: 23 | I9: 210.75 | J9: =H9*I9 | K9: 0.2 | L9: =J9*K9 | M9: =J9-L9 | N9: =J9*0.58 | O9: =M9-N9 | P9: =O9/M9 | Q9: 2026-04-17 | R9: 2026-04-30 | S9: =DATEDIF(Q9, R9, "d") | T9: =EOMONTH(Q9, 0) | U9: =NOW() | V9: =IF(ISNUMBER(MATCH(C9, $X$5:$X$18, 0)), "VIP Match", "Standard") | X9: Customer 005
A10: TXN-2006 | B10: 2026-01-20 | C10: Customer 018 | D10: Retail | E10: West | F10: AI Insights Engine | G10: =UPPER(LEFT(F10, 3)) & "-" & TEXT(LEN(F10), "00") | H10: 84 | I10: 93.72 | J10: =H10*I10 | K10: 0 | L10: =J10*K10 | M10: =J10-L10 | N10: =J10*0.62 | O10: =M10-N10 | P10: =O10/M10 | Q10: 2026-01-20 | R10: 2026-01-23 | S10: =DATEDIF(Q10, R10, "d") | T10: =EOMONTH(Q10, 0) | U10: =NOW() | V10: =IF(ISNUMBER(MATCH(C10, $X$5:$X$18, 0)), "VIP Match", "Standard") | X10: Customer 006
A11: TXN-2007 | B11: 2026-05-03 | C11: Customer 036 | D11: Corporate | E11: East | F11: AI Insights Engine | G11: =UPPER(LEFT(F11, 3)) & "-" & TEXT(LEN(F11), "00") | H11: 65 | I11: 144.4 | J11: =H11*I11 | K11: 0.15 | L11: =J11*K11 | M11: =J11-L11 | N11: =J11*0.59 | O11: =M11-N11 | P11: =O11/M11 | Q11: 2026-05-03 | R11: 2026-05-14 | S11: =DATEDIF(Q11, R11, "d") | T11: =EOMONTH(Q11, 0) | U11: =NOW() | V11: =IF(ISNUMBER(MATCH(C11, $X$5:$X$18, 0)), "VIP Match", "Standard") | X11: Customer 007
A12: TXN-2008 | B12: 2026-05-19 | C12: Customer 024 | D12: Corporate | E12: South | F12: Data Vault Ultra | G12: =UPPER(LEFT(F12, 3)) & "-" & TEXT(LEN(F12), "00") | H12: 23 | I12: 275.05 | J12: =H12*I12 | K12: 0.2 | L12: =J12*K12 | M12: =J12-L12 | N12: =J12*0.59 | O12: =M12-N12 | P12: =O12/M12 | Q12: 2026-05-19 | R12: 2026-05-21 | S12: =DATEDIF(Q12, R12, "d") | T12: =EOMONTH(Q12, 0) | U12: =NOW() | V12: =IF(ISNUMBER(MATCH(C12, $X$5:$X$18, 0)), "VIP Match", "Standard") | X12: Customer 008
A13: TXN-2009 | B13: 2026-05-01 | C13: Customer 031 | D13: Enterprise | E13: Central | F13: AI Insights Engine | G13: =UPPER(LEFT(F13, 3)) & "-" & TEXT(LEN(F13), "00") | H13: 88 | I13: 477.17 | J13: =H13*I13 | K13: 0.1 | L13: =J13*K13 | M13: =J13-L13 | N13: =J13*0.54 | O13: =M13-N13 | P13: =O13/M13 | Q13: 2026-05-01 | R13: 2026-05-05 | S13: =DATEDIF(Q13, R13, "d") | T13: =EOMONTH(Q13, 0) | U13: =NOW() | V13: =IF(ISNUMBER(MATCH(C13, $X$5:$X$18, 0)), "VIP Match", "Standard") | X13: Customer 009
A14: TXN-2010 | B14: 2026-02-16 | C14: Customer 007 | D14: Retail | E14: West | F14: Smart Metrics Dashboard | G14: =UPPER(LEFT(F14, 3)) & "-" & TEXT(LEN(F14), "00") | H14: 28 | I14: 204.97 | J14: =H14*I14 | K14: 0.1 | L14: =J14*K14 | M14: =J14-L14 | N14: =J14*0.58 | O14: =M14-N14 | P14: =O14/M14 | Q14: 2026-02-16 | R14: 2026-02-20 | S14: =DATEDIF(Q14, R14, "d") | T14: =EOMONTH(Q14, 0) | U14: =NOW() | V14: =IF(ISNUMBER(MATCH(C14, $X$5:$X$18, 0)), "VIP Match", "Standard") | X14: Customer 010
A15: TXN-2011 | B15: 2026-01-28 | C15: Customer 047 | D15: Retail | E15: East | F15: Cloud Intelligence Suite | G15: =UPPER(LEFT(F15, 3)) & "-" & TEXT(LEN(F15), "00") | H15: 28 | I15: 312.34 | J15: =H15*I15 | K15: 0.2 | L15: =J15*K15 | M15: =J15-L15 | N15: =J15*0.49 | O15: =M15-N15 | P15: =O15/M15 | Q15: 2026-01-28 | R15: 2026-02-09 | S15: =DATEDIF(Q15, R15, "d") | T15: =EOMONTH(Q15, 0) | U15: =NOW() | V15: =IF(ISNUMBER(MATCH(C15, $X$5:$X$18, 0)), "VIP Match", "Standard") | X15: Customer 011
A16: TXN-2012 | B16: 2026-05-08 | C16: Customer 006 | D16: Wholesale | E16: South | F16: Data Vault Ultra | G16: =UPPER(LEFT(F16, 3)) & "-" & TEXT(LEN(F16), "00") | H16: 82 | I16: 484.52 | J16: =H16*I16 | K16: 0 | L16: =J16*K16 | M16: =J16-L16 | N16: =J16*0.58 | O16: =M16-N16 | P16: =O16/M16 | Q16: 2026-05-08 | R16: 2026-05-10 | S16: =DATEDIF(Q16, R16, "d") | T16: =EOMONTH(Q16, 0) | U16: =NOW() | V16: =IF(ISNUMBER(MATCH(C16, $X$5:$X$18, 0)), "VIP Match", "Standard") | X16: Customer 012
A17: TXN-2013 | B17: 2026-01-30 | C17: Customer 024 | D17: Retail | E17: South | F17: Enterprise Analytics Pro | G17: =UPPER(LEFT(F17, 3)) & "-" & TEXT(LEN(F17), "00") | H17: 25 | I17: 369.74 | J17: =H17*I17 | K17: 0.2 | L17: =J17*K17 | M17: =J17-L17 | N17: =J17*0.47 | O17: =M17-N17 | P17: =O17/M17 | Q17: 2026-01-30 | R17: 2026-02-12 | S17: =DATEDIF(Q17, R17, "d") | T17: =EOMONTH(Q17, 0) | U17: =NOW() | V17: =IF(ISNUMBER(MATCH(C17, $X$5:$X$18, 0)), "VIP Match", "Standard") | X17: Customer 013
A18: TXN-2014 | B18: 2026-03-09 | C18: Customer 012 | D18: Retail | E18: West | F18: Cloud Intelligence Suite | G18: =UPPER(LEFT(F18, 3)) & "-" & TEXT(LEN(F18), "00") | H18: 29 | I18: 179.85 | J18: =H18*I18 | K18: 0.05 | L18: =J18*K18 | M18: =J18-L18 | N18: =J18*0.48 | O18: =M18-N18 | P18: =O18/M18 | Q18: 2026-03-09 | R18: 2026-03-21 | S18: =DATEDIF(Q18, R18, "d") | T18: =EOMONTH(Q18, 0) | U18: =NOW() | V18: =IF(ISNUMBER(MATCH(C18, $X$5:$X$18, 0)), "VIP Match", "Standard") | X18: Customer 014
A19: TXN-2015 | B19: 2026-05-26 | C19: Customer 002 | D19: Enterprise | E19: Central | F19: Smart Metrics Dashboard | G19: =UPPER(LEFT(F19, 3)) & "-" & TEXT(LEN(F19), "00") | H19: 105 | I19: 466.43 | J19: =H19*I19 | K19: 0.15 | L19: =J19*K19 | M19: =J19-L19 | N19: =J19*0.53 | O19: =M19-N19 | P19: =O19/M19 | Q19: 2026-05-26 | R19: 2026-06-03 | S19: =DATEDIF(Q19, R19, "d") | T19: =EOMONTH(Q19, 0) | U19: =NOW() | V19: =IF(ISNUMBER(MATCH(C19, $X$5:$X$18, 0)), "VIP Match", "Standard")
A20: TXN-2016 | B20: 2026-06-01 | C20: Customer 047 | D20: Retail | E20: North | F20: Smart Metrics Dashboard | G20: =UPPER(LEFT(F20, 3)) & "-" & TEXT(LEN(F20), "00") | H20: 15 | I20: 274.38 | J20: =H20*I20 | K20: 0 | L20: =J20*K20 | M20: =J20-L20 | N20: =J20*0.49 | O20: =M20-N20 | P20: =O20/M20 | Q20: 2026-06-01 | R20: 2026-06-08 | S20: =DATEDIF(Q20, R20, "d") | T20: =EOMONTH(Q20, 0) | U20: =NOW() | V20: =IF(ISNUMBER(MATCH(C20, $X$5:$X$18, 0)), "VIP Match", "Standard")
A21: TXN-2017 | B21: 2026-01-03 | C21: Customer 022 | D21: Corporate | E21: Central | F21: Data Vault Ultra | G21: =UPPER(LEFT(F21, 3)) & "-" & TEXT(LEN(F21), "00") | H21: 109 | I21: 344.02 | J21: =H21*I21 | K21: 0.05 | L21: =J21*K21 | M21: =J21-L21 | N21: =J21*0.54 | O21: =M21-N21 | P21: =O21/M21 | Q21: 2026-01-03 | R21: 2026-01-04 | S21: =DATEDIF(Q21, R21, "d") | T21: =EOMONTH(Q21, 0) | U21: =NOW() | V21: =IF(ISNUMBER(MATCH(C21, $X$5:$X$18, 0)), "VIP Match", "Standard")
A22: TXN-2018 | B22: 2026-06-03 | C22: Customer 003 | D22: Retail | E22: South | F22: Smart Metrics Dashboard | G22: =UPPER(LEFT(F22, 3)) & "-" & TEXT(LEN(F22), "00") | H22: 47 | I22: 296.64 | J22: =H22*I22 | K22: 0.2 | L22: =J22*K22 | M22: =J22-L22 | N22: =J22*0.49 | O22: =M22-N22 | P22: =O22/M22 | Q22: 2026-06-03 | R22: 2026-06-05 | S22: =DATEDIF(Q22, R22, "d") | T22: =EOMONTH(Q22, 0) | U22: =NOW() | V22: =IF(ISNUMBER(MATCH(C22, $X$5:$X$18, 0)), "VIP Match", "Standard")
A23: TXN-2019 | B23: 2026-04-14 | C23: Customer 047 | D23: Corporate | E23: West | F23: Enterprise Analytics Pro | G23: =UPPER(LEFT(F23, 3)) & "-" & TEXT(LEN(F23), "00") | H23: 85 | I23: 369.88 | J23: =H23*I23 | K23: 0.2 | L23: =J23*K23 | M23: =J23-L23 | N23: =J23*0.61 | O23: =M23-N23 | P23: =O23/M23 | Q23: 2026-04-14 | R23: 2026-04-15 | S23: =DATEDIF(Q23, R23, "d") | T23: =EOMONTH(Q23, 0) | U23: =NOW() | V23: =IF(ISNUMBER(MATCH(C23, $X$5:$X$18, 0)), "VIP Match", "Standard")
A24: TXN-2020 | B24: 2026-04-24 | C24: Customer 039 | D24: Wholesale | E24: Central | F24: AI Insights Engine | G24: =UPPER(LEFT(F24, 3)) & "-" & TEXT(LEN(F24), "00") | H24: 30 | I24: 433.69 | J24: =H24*I24 | K24: 0 | L24: =J24*K24 | M24: =J24-L24 | N24: =J24*0.57 | O24: =M24-N24 | P24: =O24/M24 | Q24: 2026-04-24 | R24: 2026-05-06 | S24: =DATEDIF(Q24, R24, "d") | T24: =EOMONTH(Q24, 0) | U24: =NOW() | V24: =IF(ISNUMBER(MATCH(C24, $X$5:$X$18, 0)), "VIP Match", "Standard")
A25: TXN-2021 | B25: 2026-02-05 | C25: Customer 048 | D25: Corporate | E25: West | F25: Data Vault Ultra | G25: =UPPER(LEFT(F25, 3)) & "-" & TEXT(LEN(F25), "00") | H25: 107 | I25: 442.67 | J25: =H25*I25 | K25: 0.05 | L25: =J25*K25 | M25: =J25-L25 | N25: =J25*0.46 | O25: =M25-N25 | P25: =O25/M25 | Q25: 2026-02-05 | R25: 2026-02-16 | S25: =DATEDIF(Q25, R25, "d") | T25: =EOMONTH(Q25, 0) | U25: =NOW() | V25: =IF(ISNUMBER(MATCH(C25, $X$5:$X$18, 0)), "VIP Match", "Standard")
A26: TXN-2022 | B26: 2026-04-10 | C26: Customer 038 | D26: Retail | E26: East | F26: Smart Metrics Dashboard | G26: =UPPER(LEFT(F26, 3)) & "-" & TEXT(LEN(F26), "00") | H26: 54 | I26: 402.39 | J26: =H26*I26 | K26: 0.15 | L26: =J26*K26 | M26: =J26-L26 | N26: =J26*0.45 | O26: =M26-N26 | P26: =O26/M26 | Q26: 2026-04-10 | R26: 2026-04-19 | S26: =DATEDIF(Q26, R26, "d") | T26: =EOMONTH(Q26, 0) | U26: =NOW() | V26: =IF(ISNUMBER(MATCH(C26, $X$5:$X$18, 0)), "VIP Match", "Standard")
A27: TXN-2023 | B27: 2026-03-09 | C27: Customer 025 | D27: Corporate | E27: South | F27: Smart Metrics Dashboard | G27: =UPPER(LEFT(F27, 3)) & "-" & TEXT(LEN(F27), "00") | H27: 22 | I27: 88.25 | J27: =H27*I27 | K27: 0.15 | L27: =J27*K27 | M27: =J27-L27 | N27: =J27*0.58 | O27: =M27-N27 | P27: =O27/M27 | Q27: 2026-03-09 | R27: 2026-03-22 | S27: =DATEDIF(Q27, R27, "d") | T27: =EOMONTH(Q27, 0) | U27: =NOW() | V27: =IF(ISNUMBER(MATCH(C27, $X$5:$X$18, 0)), "VIP Match", "Standard")
A28: TXN-2024 | B28: 2026-05-04 | C28: Customer 035 | D28: Enterprise | E28: Central | F28: Cloud Intelligence Suite | G28: =UPPER(LEFT(F28, 3)) & "-" & TEXT(LEN(F28), "00") | H28: 25 | I28: 195.15 | J28: =H28*I28 | K28: 0.05 | L28: =J28*K28 | M28: =J28-L28 | N28: =J28*0.49 | O28: =M28-N28 | P28: =O28/M28 | Q28: 2026-05-04 | R28: 2026-05-10 | S28: =DATEDIF(Q28, R28, "d") | T28: =EOMONTH(Q28, 0) | U28: =NOW() | V28: =IF(ISNUMBER(MATCH(C28, $X$5:$X$18, 0)), "VIP Match", "Standard")
A29: TXN-2025 | B29: 2026-06-08 | C29: Customer 026 | D29: Corporate | E29: Central | F29: Data Vault Ultra | G29: =UPPER(LEFT(F29, 3)) & "-" & TEXT(LEN(F29), "00") | H29: 80 | I29: 462.86 | J29: =H29*I29 | K29: 0.15 | L29: =J29*K29 | M29: =J29-L29 | N29: =J29*0.49 | O29: =M29-N29 | P29: =O29/M29 | Q29: 2026-06-08 | R29: 2026-06-12 | S29: =DATEDIF(Q29, R29, "d") | T29: =EOMONTH(Q29, 0) | U29: =NOW() | V29: =IF(ISNUMBER(MATCH(C29, $X$5:$X$18, 0)), "VIP Match", "Standard")
A30: TXN-2026 | B30: 2026-05-15 | C30: Customer 047 | D30: Wholesale | E30: North | F30: AI Insights Engine | G30: =UPPER(LEFT(F30, 3)) & "-" & TEXT(LEN(F30), "00") | H30: 86 | I30: 108.74 | J30: =H30*I30 | K30: 0.05 | L30: =J30*K30 | M30: =J30-L30 | N30: =J30*0.58 | O30: =M30-N30 | P30: =O30/M30 | Q30: 2026-05-15 | R30: 2026-05-22 | S30: =DATEDIF(Q30, R30, "d") | T30: =EOMONTH(Q30, 0) | U30: =NOW() | V30: =IF(ISNUMBER(MATCH(C30, $X$5:$X$18, 0)), "VIP Match", "Standard")
A31: TXN-2027 | B31: 2026-06-10 | C31: Customer 048 | D31: Enterprise | E31: Central | F31: AI Insights Engine | G31: =UPPER(LEFT(F31, 3)) & "-" & TEXT(LEN(F31), "00") | H31: 102 | I31: 427.35 | J31: =H31*I31 | K31: 0.1 | L31: =J31*K31 | M31: =J31-L31 | N31: =J31*0.65 | O31: =M31-N31 | P31: =O31/M31 | Q31: 2026-06-10 | R31: 2026-06-18 | S31: =DATEDIF(Q31, R31, "d") | T31: =EOMONTH(Q31, 0) | U31: =NOW() | V31: =IF(ISNUMBER(MATCH(C31, $X$5:$X$18, 0)), "VIP Match", "Standard")
A32: TXN-2028 | B32: 2026-06-10 | C32: Customer 015 | D32: Retail | E32: East | F32: Enterprise Analytics Pro | G32: =UPPER(LEFT(F32, 3)) & "-" & TEXT(LEN(F32), "00") | H32: 25 | I32: 377.24 | J32: =H32*I32 | K32: 0.05 | L32: =J32*K32 | M32: =J32-L32 | N32: =J32*0.54 | O32: =M32-N32 | P32: =O32/M32 | Q32: 2026-06-10 | R32: 2026-06-21 | S32: =DATEDIF(Q32, R32, "d") | T32: =EOMONTH(Q32, 0) | U32: =NOW() | V32: =IF(ISNUMBER(MATCH(C32, $X$5:$X$18, 0)), "VIP Match", "Standard")
A33: TXN-2029 | B33: 2026-05-31 | C33: Customer 032 | D33: Wholesale | E33: East | F33: Enterprise Analytics Pro | G33: =UPPER(LEFT(F33, 3)) & "-" & TEXT(LEN(F33), "00") | H33: 46 | I33: 363.95 | J33: =H33*I33 | K33: 0 | L33: =J33*K33 | M33: =J33-L33 | N33: =J33*0.45 | O33: =M33-N33 | P33: =O33/M33 | Q33: 2026-05-31 | R33: 2026-06-01 | S33: =DATEDIF(Q33, R33, "d") | T33: =EOMONTH(Q33, 0) | U33: =NOW() | V33: =IF(ISNUMBER(MATCH(C33, $X$5:$X$18, 0)), "VIP Match", "Standard")
A34: TXN-2030 | B34: 2026-03-18 | C34: Customer 004 | D34: Retail | E34: South | F34: Data Vault Ultra | G34: =UPPER(LEFT(F34, 3)) & "-" & TEXT(LEN(F34), "00") | H34: 100 | I34: 329.31 | J34: =H34*I34 | K34: 0 | L34: =J34*K34 | M34: =J34-L34 | N34: =J34*0.53 | O34: =M34-N34 | P34: =O34/M34 | Q34: 2026-03-18 | R34: 2026-03-22 | S34: =DATEDIF(Q34, R34, "d") | T34: =EOMONTH(Q34, 0) | U34: =NOW() | V34: =IF(ISNUMBER(MATCH(C34, $X$5:$X$18, 0)), "VIP Match", "Standard")
A35: TXN-2031 | B35: 2026-03-28 | C35: Customer 032 | D35: Enterprise | E35: Central | F35: AI Insights Engine | G35: =UPPER(LEFT(F35, 3)) & "-" & TEXT(LEN(F35), "00") | H35: 57 | I35: 85.32 | J35: =H35*I35 | K35: 0.1 | L35: =J35*K35 | M35: =J35-L35 | N35: =J35*0.63 | O35: =M35-N35 | P35: =O35/M35 | Q35: 2026-03-28 | R35: 2026-03-30 | S35: =DATEDIF(Q35, R35, "d") | T35: =EOMONTH(Q35, 0) | U35: =NOW() | V35: =IF(ISNUMBER(MATCH(C35, $X$5:$X$18, 0)), "VIP Match", "Standard")
A36: TXN-2032 | B36: 2026-04-08 | C36: Customer 034 | D36: Corporate | E36: South | F36: Cloud Intelligence Suite | G36: =UPPER(LEFT(F36, 3)) & "-" & TEXT(LEN(F36), "00") | H36: 45 | I36: 203.91 | J36: =H36*I36 | K36: 0 | L36: =J36*K36 | M36: =J36-L36 | N36: =J36*0.49 | O36: =M36-N36 | P36: =O36/M36 | Q36: 2026-04-08 | R36: 2026-04-16 | S36: =DATEDIF(Q36, R36, "d") | T36: =EOMONTH(Q36, 0) | U36: =NOW() | V36: =IF(ISNUMBER(MATCH(C36, $X$5:$X$18, 0)), "VIP Match", "Standard")
A37: TXN-2033 | B37: 2026-06-12 | C37: Customer 041 | D37: Enterprise | E37: Central | F37: Data Vault Ultra | G37: =UPPER(LEFT(F37, 3)) & "-" & TEXT(LEN(F37), "00") | H37: 99 | I37: 95 | J37: =H37*I37 | K37: 0 | L37: =J37*K37 | M37: =J37-L37 | N37: =J37*0.45 | O37: =M37-N37 | P37: =O37/M37 | Q37: 2026-06-12 | R37: 2026-06-21 | S37: =DATEDIF(Q37, R37, "d") | T37: =EOMONTH(Q37, 0) | U37: =NOW() | V37: =IF(ISNUMBER(MATCH(C37, $X$5:$X$18, 0)), "VIP Match", "Standard")
A38: TXN-2034 | B38: 2026-01-18 | C38: Customer 006 | D38: Corporate | E38: West | F38: AI Insights Engine | G38: =UPPER(LEFT(F38, 3)) & "-" & TEXT(LEN(F38), "00") | H38: 31 | I38: 353.25 | J38: =H38*I38 | K38: 0.15 | L38: =J38*K38 | M38: =J38-L38 | N38: =J38*0.62 | O38: =M38-N38 | P38: =O38/M38 | Q38: 2026-01-18 | R38: 2026-01-30 | S38: =DATEDIF(Q38, R38, "d") | T38: =EOMONTH(Q38, 0) | U38: =NOW() | V38: =IF(ISNUMBER(MATCH(C38, $X$5:$X$18, 0)), "VIP Match", "Standard")
A39: TXN-2035 | B39: 2026-02-23 | C39: Customer 001 | D39: Wholesale | E39: Central | F39: Smart Metrics Dashboard | G39: =UPPER(LEFT(F39, 3)) & "-" & TEXT(LEN(F39), "00") | H39: 56 | I39: 421.66 | J39: =H39*I39 | K39: 0.1 | L39: =J39*K39 | M39: =J39-L39 | N39: =J39*0.48 | O39: =M39-N39 | P39: =O39/M39 | Q39: 2026-02-23 | R39: 2026-03-05 | S39: =DATEDIF(Q39, R39, "d") | T39: =EOMONTH(Q39, 0) | U39: =NOW() | V39: =IF(ISNUMBER(MATCH(C39, $X$5:$X$18, 0)), "VIP Match", "Standard")
A40: TXN-2036 | B40: 2026-02-06 | C40: Customer 006 | D40: Wholesale | E40: North | F40: AI Insights Engine | G40: =UPPER(LEFT(F40, 3)) & "-" & TEXT(LEN(F40), "00") | H40: 20 | I40: 453 | J40: =H40*I40 | K40: 0.15 | L40: =J40*K40 | M40: =J40-L40 | N40: =J40*0.62 | O40: =M40-N40 | P40: =O40/M40 | Q40: 2026-02-06 | R40: 2026-02-18 | S40: =DATEDIF(Q40, R40, "d") | T40: =EOMONTH(Q40, 0) | U40: =NOW() | V40: =IF(ISNUMBER(MATCH(C40, $X$5:$X$18, 0)), "VIP Match", "Standard")
A41: TXN-2037 | B41: 2026-03-17 | C41: Customer 028 | D41: Corporate | E41: South | F41: AI Insights Engine | G41: =UPPER(LEFT(F41, 3)) & "-" & TEXT(LEN(F41), "00") | H41: 60 | I41: 377.2 | J41: =H41*I41 | K41: 0.15 | L41: =J41*K41 | M41: =J41-L41 | N41: =J41*0.50 | O41: =M41-N41 | P41: =O41/M41 | Q41: 2026-03-17 | R41: 2026-03-23 | S41: =DATEDIF(Q41, R41, "d") | T41: =EOMONTH(Q41, 0) | U41: =NOW() | V41: =IF(ISNUMBER(MATCH(C41, $X$5:$X$18, 0)), "VIP Match", "Standard")
A42: TXN-2038 | B42: 2026-04-02 | C42: Customer 045 | D42: Wholesale | E42: Central | F42: Smart Metrics Dashboard | G42: =UPPER(LEFT(F42, 3)) & "-" & TEXT(LEN(F42), "00") | H42: 110 | I42: 89.79 | J42: =H42*I42 | K42: 0.05 | L42: =J42*K42 | M42: =J42-L42 | N42: =J42*0.49 | O42: =M42-N42 | P42: =O42/M42 | Q42: 2026-04-02 | R42: 2026-04-06 | S42: =DATEDIF(Q42, R42, "d") | T42: =EOMONTH(Q42, 0) | U42: =NOW() | V42: =IF(ISNUMBER(MATCH(C42, $X$5:$X$18, 0)), "VIP Match", "Standard")
A43: TXN-2039 | B43: 2026-06-19 | C43: Customer 046 | D43: Wholesale | E43: East | F43: Smart Metrics Dashboard | G43: =UPPER(LEFT(F43, 3)) & "-" & TEXT(LEN(F43), "00") | H43: 66 | I43: 202.29 | J43: =H43*I43 | K43: 0 | L43: =J43*K43 | M43: =J43-L43 | N43: =J43*0.52 | O43: =M43-N43 | P43: =O43/M43 | Q43: 2026-06-19 | R43: 2026-06-28 | S43: =DATEDIF(Q43, R43, "d") | T43: =EOMONTH(Q43, 0) | U43: =NOW() | V43: =IF(ISNUMBER(MATCH(C43, $X$5:$X$18, 0)), "VIP Match", "Standard")
A44: TXN-2040 | B44: 2026-03-30 | C44: Customer 030 | D44: Retail | E44: West | F44: Enterprise Analytics Pro | G44: =UPPER(LEFT(F44, 3)) & "-" & TEXT(LEN(F44), "00") | H44: 74 | I44: 103.71 | J44: =H44*I44 | K44: 0.1 | L44: =J44*K44 | M44: =J44-L44 | N44: =J44*0.49 | O44: =M44-N44 | P44: =O44/M44 | Q44: 2026-03-30 | R44: 2026-04-05 | S44: =DATEDIF(Q44, R44, "d") | T44: =EOMONTH(Q44, 0) | U44: =NOW() | V44: =IF(ISNUMBER(MATCH(C44, $X$5:$X$18, 0)), "VIP Match", "Standard")
A45: TXN-2041 | B45: 2026-02-26 | C45: Customer 047 | D45: Corporate | E45: West | F45: Smart Metrics Dashboard | G45: =UPPER(LEFT(F45, 3)) & "-" & TEXT(LEN(F45), "00") | H45: 26 | I45: 104.77 | J45: =H45*I45 | K45: 0.2 | L45: =J45*K45 | M45: =J45-L45 | N45: =J45*0.49 | O45: =M45-N45 | P45: =O45/M45 | Q45: 2026-02-26 | R45: 2026-02-28 | S45: =DATEDIF(Q45, R45, "d") | T45: =EOMONTH(Q45, 0) | U45: =NOW() | V45: =IF(ISNUMBER(MATCH(C45, $X$5:$X$18, 0)), "VIP Match", "Standard")
A46: TXN-2042 | B46: 2026-02-11 | C46: Customer 030 | D46: Corporate | E46: East | F46: Enterprise Analytics Pro | G46: =UPPER(LEFT(F46, 3)) & "-" & TEXT(LEN(F46), "00") | H46: 65 | I46: 315.25 | J46: =H46*I46 | K46: 0.15 | L46: =J46*K46 | M46: =J46-L46 | N46: =J46*0.56 | O46: =M46-N46 | P46: =O46/M46 | Q46: 2026-02-11 | R46: 2026-02-20 | S46: =DATEDIF(Q46, R46, "d") | T46: =EOMONTH(Q46, 0) | U46: =NOW() | V46: =IF(ISNUMBER(MATCH(C46, $X$5:$X$18, 0)), "VIP Match", "Standard")
A47: TXN-2043 | B47: 2026-05-25 | C47: Customer 046 | D47: Corporate | E47: South | F47: Smart Metrics Dashboard | G47: =UPPER(LEFT(F47, 3)) & "-" & TEXT(LEN(F47), "00") | H47: 94 | I47: 108.61 | J47: =H47*I47 | K47: 0.05 | L47: =J47*K47 | M47: =J47-L47 | N47: =J47*0.58 | O47: =M47-N47 | P47: =O47/M47 | Q47: 2026-05-25 | R47: 2026-05-27 | S47: =DATEDIF(Q47, R47, "d") | T47: =EOMONTH(Q47, 0) | U47: =NOW() | V47: =IF(ISNUMBER(MATCH(C47, $X$5:$X$18, 0)), "VIP Match", "Standard")
A48: TXN-2044 | B48: 2026-05-10 | C48: Customer 032 | D48: Wholesale | E48: East | F48: AI Insights Engine | G48: =UPPER(LEFT(F48, 3)) & "-" & TEXT(LEN(F48), "00") | H48: 91 | I48: 299.99 | J48: =H48*I48 | K48: 0.15 | L48: =J48*K48 | M48: =J48-L48 | N48: =J48*0.64 | O48: =M48-N48 | P48: =O48/M48 | Q48: 2026-05-10 | R48: 2026-05-11 | S48: =DATEDIF(Q48, R48, "d") | T48: =EOMONTH(Q48, 0) | U48: =NOW() | V48: =IF(ISNUMBER(MATCH(C48, $X$5:$X$18, 0)), "VIP Match", "Standard")
A49: TXN-2045 | B49: 2026-04-15 | C49: Customer 024 | D49: Retail | E49: West | F49: Cloud Intelligence Suite | G49: =UPPER(LEFT(F49, 3)) & "-" & TEXT(LEN(F49), "00") | H49: 17 | I49: 465.32 | J49: =H49*I49 | K49: 0.1 | L49: =J49*K49 | M49: =J49-L49 | N49: =J49*0.48 | O49: =M49-N49 | P49: =O49/M49 | Q49: 2026-04-15 | R49: 2026-04-17 | S49: =DATEDIF(Q49, R49, "d") | T49: =EOMONTH(Q49, 0) | U49: =NOW() | V49: =IF(ISNUMBER(MATCH(C49, $X$5:$X$18, 0)), "VIP Match", "Standard")
A50: TXN-2046 | B50: 2026-05-18 | C50: Customer 001 | D50: Retail | E50: West | F50: Enterprise Analytics Pro | G50: =UPPER(LEFT(F50, 3)) & "-" & TEXT(LEN(F50), "00") | H50: 64 | I50: 281.2 | J50: =H50*I50 | K50: 0 | L50: =J50*K50 | M50: =J50-L50 | N50: =J50*0.54 | O50: =M50-N50 | P50: =O50/M50 | Q50: 2026-05-18 | R50: 2026-05-22 | S50: =DATEDIF(Q50, R50, "d") | T50: =EOMONTH(Q50, 0) | U50: =NOW() | V50: =IF(ISNUMBER(MATCH(C50, $X$5:$X$18, 0)), "VIP Match", "Standard")
A51: TXN-2047 | B51: 2026-02-21 | C51: Customer 045 | D51: Enterprise | E51: East | F51: Cloud Intelligence Suite | G51: =UPPER(LEFT(F51, 3)) & "-" & TEXT(LEN(F51), "00") | H51: 55 | I51: 54.32 | J51: =H51*I51 | K51: 0.2 | L51: =J51*K51 | M51: =J51-L51 | N51: =J51*0.51 | O51: =M51-N51 | P51: =O51/M51 | Q51: 2026-02-21 | R51: 2026-03-02 | S51: =DATEDIF(Q51, R51, "d") | T51: =EOMONTH(Q51, 0) | U51: =NOW() | V51: =IF(ISNUMBER(MATCH(C51, $X$5:$X$18, 0)), "VIP Match", "Standard")
A52: TXN-2048 | B52: 2026-01-08 | C52: Customer 039 | D52: Retail | E52: Central | F52: Smart Metrics Dashboard | G52: =UPPER(LEFT(F52, 3)) & "-" & TEXT(LEN(F52), "00") | H52: 106 | I52: 435.23 | J52: =H52*I52 | K52: 0.2 | L52: =J52*K52 | M52: =J52-L52 | N52: =J52*0.58 | O52: =M52-N52 | P52: =O52/M52 | Q52: 2026-01-08 | R52: 2026-01-14 | S52: =DATEDIF(Q52, R52, "d") | T52: =EOMONTH(Q52, 0) | U52: =NOW() | V52: =IF(ISNUMBER(MATCH(C52, $X$5:$X$18, 0)), "VIP Match", "Standard")
A53: TXN-2049 | B53: 2026-06-20 | C53: Customer 045 | D53: Corporate | E53: South | F53: Smart Metrics Dashboard | G53: =UPPER(LEFT(F53, 3)) & "-" & TEXT(LEN(F53), "00") | H53: 103 | I53: 464.12 | J53: =H53*I53 | K53: 0.15 | L53: =J53*K53 | M53: =J53-L53 | N53: =J53*0.57 | O53: =M53-N53 | P53: =O53/M53 | Q53: 2026-06-20 | R53: 2026-06-23 | S53: =DATEDIF(Q53, R53, "d") | T53: =EOMONTH(Q53, 0) | U53: =NOW() | V53: =IF(ISNUMBER(MATCH(C53, $X$5:$X$18, 0)), "VIP Match", "Standard")
A54: TXN-2050 | B54: 2026-05-12 | C54: Customer 010 | D54: Wholesale | E54: East | F54: Data Vault Ultra | G54: =UPPER(LEFT(F54, 3)) & "-" & TEXT(LEN(F54), "00") | H54: 27 | I54: 434.58 | J54: =H54*I54 | K54: 0.2 | L54: =J54*K54 | M54: =J54-L54 | N54: =J54*0.52 | O54: =M54-N54 | P54: =O54/M54 | Q54: 2026-05-12 | R54: 2026-05-19 | S54: =DATEDIF(Q54, R54, "d") | T54: =EOMONTH(Q54, 0) | U54: =NOW() | V54: =IF(ISNUMBER(MATCH(C54, $X$5:$X$18, 0)), "VIP Match", "Standard")
A55: TXN-2051 | B55: 2026-01-21 | C55: Customer 037 | D55: Enterprise | E55: South | F55: Data Vault Ultra | G55: =UPPER(LEFT(F55, 3)) & "-" & TEXT(LEN(F55), "00") | H55: 42 | I55: 286.43 | J55: =H55*I55 | K55: 0 | L55: =J55*K55 | M55: =J55-L55 | N55: =J55*0.63 | O55: =M55-N55 | P55: =O55/M55 | Q55: 2026-01-21 | R55: 2026-01-31 | S55: =DATEDIF(Q55, R55, "d") | T55: =EOMONTH(Q55, 0) | U55: =NOW() | V55: =IF(ISNUMBER(MATCH(C55, $X$5:$X$18, 0)), "VIP Match", "Standard")
A56: TXN-2052 | B56: 2026-02-11 | C56: Customer 024 | D56: Retail | E56: North | F56: Smart Metrics Dashboard | G56: =UPPER(LEFT(F56, 3)) & "-" & TEXT(LEN(F56), "00") | H56: 77 | I56: 362.93 | J56: =H56*I56 | K56: 0 | L56: =J56*K56 | M56: =J56-L56 | N56: =J56*0.50 | O56: =M56-N56 | P56: =O56/M56 | Q56: 2026-02-11 | R56: 2026-02-16 | S56: =DATEDIF(Q56, R56, "d") | T56: =EOMONTH(Q56, 0) | U56: =NOW() | V56: =IF(ISNUMBER(MATCH(C56, $X$5:$X$18, 0)), "VIP Match", "Standard")
A57: TXN-2053 | B57: 2026-05-17 | C57: Customer 015 | D57: Enterprise | E57: East | F57: Smart Metrics Dashboard | G57: =UPPER(LEFT(F57, 3)) & "-" & TEXT(LEN(F57), "00") | H57: 75 | I57: 356.95 | J57: =H57*I57 | K57: 0.1 | L57: =J57*K57 | M57: =J57-L57 | N57: =J57*0.51 | O57: =M57-N57 | P57: =O57/M57 | Q57: 2026-05-17 | R57: 2026-05-23 | S57: =DATEDIF(Q57, R57, "d") | T57: =EOMONTH(Q57, 0) | U57: =NOW() | V57: =IF(ISNUMBER(MATCH(C57, $X$5:$X$18, 0)), "VIP Match", "Standard")
A58: TXN-2054 | B58: 2026-06-23 | C58: Customer 048 | D58: Corporate | E58: North | F58: Enterprise Analytics Pro | G58: =UPPER(LEFT(F58, 3)) & "-" & TEXT(LEN(F58), "00") | H58: 63 | I58: 296.88 | J58: =H58*I58 | K58: 0.1 | L58: =J58*K58 | M58: =J58-L58 | N58: =J58*0.61 | O58: =M58-N58 | P58: =O58/M58 | Q58: 2026-06-23 | R58: 2026-07-06 | S58: =DATEDIF(Q58, R58, "d") | T58: =EOMONTH(Q58, 0) | U58: =NOW() | V58: =IF(ISNUMBER(MATCH(C58, $X$5:$X$18, 0)), "VIP Match", "Standard")
A59: TXN-2055 | B59: 2026-05-07 | C59: Customer 048 | D59: Wholesale | E59: East | F59: Smart Metrics Dashboard | G59: =UPPER(LEFT(F59, 3)) & "-" & TEXT(LEN(F59), "00") | H59: 67 | I59: 216.18 | J59: =H59*I59 | K59: 0.15 | L59: =J59*K59 | M59: =J59-L59 | N59: =J59*0.50 | O59: =M59-N59 | P59: =O59/M59 | Q59: 2026-05-07 | R59: 2026-05-10 | S59: =DATEDIF(Q59, R59, "d") | T59: =EOMONTH(Q59, 0) | U59: =NOW() | V59: =IF(ISNUMBER(MATCH(C59, $X$5:$X$18, 0)), "VIP Match", "Standard")
A60: TXN-2056 | B60: 2026-04-20 | C60: Customer 017 | D60: Wholesale | E60: North | F60: Data Vault Ultra | G60: =UPPER(LEFT(F60, 3)) & "-" & TEXT(LEN(F60), "00") | H60: 108 | I60: 50.2 | J60: =H60*I60 | K60: 0 | L60: =J60*K60 | M60: =J60-L60 | N60: =J60*0.58 | O60: =M60-N60 | P60: =O60/M60 | Q60: 2026-04-20 | R60: 2026-05-01 | S60: =DATEDIF(Q60, R60, "d") | T60: =EOMONTH(Q60, 0) | U60: =NOW() | V60: =IF(ISNUMBER(MATCH(C60, $X$5:$X$18, 0)), "VIP Match", "Standard")
A61: TXN-2057 | B61: 2026-05-11 | C61: Customer 039 | D61: Corporate | E61: North | F61: Smart Metrics Dashboard | G61: =UPPER(LEFT(F61, 3)) & "-" & TEXT(LEN(F61), "00") | H61: 22 | I61: 478.82 | J61: =H61*I61 | K61: 0.1 | L61: =J61*K61 | M61: =J61-L61 | N61: =J61*0.61 | O61: =M61-N61 | P61: =O61/M61 | Q61: 2026-05-11 | R61: 2026-05-14 | S61: =DATEDIF(Q61, R61, "d") | T61: =EOMONTH(Q61, 0) | U61: =NOW() | V61: =IF(ISNUMBER(MATCH(C61, $X$5:$X$18, 0)), "VIP Match", "Standard")
A62: TXN-2058 | B62: 2026-05-29 | C62: Customer 032 | D62: Corporate | E62: North | F62: Smart Metrics Dashboard | G62: =UPPER(LEFT(F62, 3)) & "-" & TEXT(LEN(F62), "00") | H62: 67 | I62: 462 | J62: =H62*I62 | K62: 0.1 | L62: =J62*K62 | M62: =J62-L62 | N62: =J62*0.56 | O62: =M62-N62 | P62: =O62/M62 | Q62: 2026-05-29 | R62: 2026-06-01 | S62: =DATEDIF(Q62, R62, "d") | T62: =EOMONTH(Q62, 0) | U62: =NOW() | V62: =IF(ISNUMBER(MATCH(C62, $X$5:$X$18, 0)), "VIP Match", "Standard")
A63: TXN-2059 | B63: 2026-01-19 | C63: Customer 003 | D63: Enterprise | E63: Central | F63: Enterprise Analytics Pro | G63: =UPPER(LEFT(F63, 3)) & "-" & TEXT(LEN(F63), "00") | H63: 11 | I63: 305.78 | J63: =H63*I63 | K63: 0.2 | L63: =J63*K63 | M63: =J63-L63 | N63: =J63*0.45 | O63: =M63-N63 | P63: =O63/M63 | Q63: 2026-01-19 | R63: 2026-01-31 | S63: =DATEDIF(Q63, R63, "d") | T63: =EOMONTH(Q63, 0) | U63: =NOW() | V63: =IF(ISNUMBER(MATCH(C63, $X$5:$X$18, 0)), "VIP Match", "Standard")
A64: TXN-2060 | B64: 2026-03-21 | C64: Customer 001 | D64: Enterprise | E64: South | F64: Data Vault Ultra | G64: =UPPER(LEFT(F64, 3)) & "-" & TEXT(LEN(F64), "00") | H64: 91 | I64: 357.75 | J64: =H64*I64 | K64: 0.2 | L64: =J64*K64 | M64: =J64-L64 | N64: =J64*0.63 | O64: =M64-N64 | P64: =O64/M64 | Q64: 2026-03-21 | R64: 2026-04-01 | S64: =DATEDIF(Q64, R64, "d") | T64: =EOMONTH(Q64, 0) | U64: =NOW() | V64: =IF(ISNUMBER(MATCH(C64, $X$5:$X$18, 0)), "VIP Match", "Standard")
A65: TXN-2061 | B65: 2026-01-06 | C65: Customer 008 | D65: Enterprise | E65: South | F65: Data Vault Ultra | G65: =UPPER(LEFT(F65, 3)) & "-" & TEXT(LEN(F65), "00") | H65: 114 | I65: 452.26 | J65: =H65*I65 | K65: 0.1 | L65: =J65*K65 | M65: =J65-L65 | N65: =J65*0.57 | O65: =M65-N65 | P65: =O65/M65 | Q65: 2026-01-06 | R65: 2026-01-10 | S65: =DATEDIF(Q65, R65, "d") | T65: =EOMONTH(Q65, 0) | U65: =NOW() | V65: =IF(ISNUMBER(MATCH(C65, $X$5:$X$18, 0)), "VIP Match", "Standard")
A66: TXN-2062 | B66: 2026-03-29 | C66: Customer 029 | D66: Corporate | E66: West | F66: Data Vault Ultra | G66: =UPPER(LEFT(F66, 3)) & "-" & TEXT(LEN(F66), "00") | H66: 96 | I66: 240.57 | J66: =H66*I66 | K66: 0.2 | L66: =J66*K66 | M66: =J66-L66 | N66: =J66*0.47 | O66: =M66-N66 | P66: =O66/M66 | Q66: 2026-03-29 | R66: 2026-04-01 | S66: =DATEDIF(Q66, R66, "d") | T66: =EOMONTH(Q66, 0) | U66: =NOW() | V66: =IF(ISNUMBER(MATCH(C66, $X$5:$X$18, 0)), "VIP Match", "Standard")
A67: TXN-2063 | B67: 2026-04-18 | C67: Customer 037 | D67: Retail | E67: South | F67: Enterprise Analytics Pro | G67: =UPPER(LEFT(F67, 3)) & "-" & TEXT(LEN(F67), "00") | H67: 12 | I67: 221.27 | J67: =H67*I67 | K67: 0.15 | L67: =J67*K67 | M67: =J67-L67 | N67: =J67*0.57 | O67: =M67-N67 | P67: =O67/M67 | Q67: 2026-04-18 | R67: 2026-05-01 | S67: =DATEDIF(Q67, R67, "d") | T67: =EOMONTH(Q67, 0) | U67: =NOW() | V67: =IF(ISNUMBER(MATCH(C67, $X$5:$X$18, 0)), "VIP Match", "Standard")
A68: TXN-2064 | B68: 2026-05-26 | C68: Customer 049 | D68: Wholesale | E68: North | F68: Cloud Intelligence Suite | G68: =UPPER(LEFT(F68, 3)) & "-" & TEXT(LEN(F68), "00") | H68: 7 | I68: 479.41 | J68: =H68*I68 | K68: 0.05 | L68: =J68*K68 | M68: =J68-L68 | N68: =J68*0.56 | O68: =M68-N68 | P68: =O68/M68 | Q68: 2026-05-26 | R68: 2026-05-27 | S68: =DATEDIF(Q68, R68, "d") | T68: =EOMONTH(Q68, 0) | U68: =NOW() | V68: =IF(ISNUMBER(MATCH(C68, $X$5:$X$18, 0)), "VIP Match", "Standard")
A69: TXN-2065 | B69: 2026-01-20 | C69: Customer 022 | D69: Wholesale | E69: South | F69: Smart Metrics Dashboard | G69: =UPPER(LEFT(F69, 3)) & "-" & TEXT(LEN(F69), "00") | H69: 41 | I69: 207.69 | J69: =H69*I69 | K69: 0 | L69: =J69*K69 | M69: =J69-L69 | N69: =J69*0.56 | O69: =M69-N69 | P69: =O69/M69 | Q69: 2026-01-20 | R69: 2026-01-22 | S69: =DATEDIF(Q69, R69, "d") | T69: =EOMONTH(Q69, 0) | U69: =NOW() | V69: =IF(ISNUMBER(MATCH(C69, $X$5:$X$18, 0)), "VIP Match", "Standard")
A70: TXN-2066 | B70: 2026-03-25 | C70: Customer 013 | D70: Retail | E70: South | F70: Smart Metrics Dashboard | G70: =UPPER(LEFT(F70, 3)) & "-" & TEXT(LEN(F70), "00") | H70: 59 | I70: 109.25 | J70: =H70*I70 | K70: 0.15 | L70: =J70*K70 | M70: =J70-L70 | N70: =J70*0.58 | O70: =M70-N70 | P70: =O70/M70 | Q70: 2026-03-25 | R70: 2026-04-02 | S70: =DATEDIF(Q70, R70, "d") | T70: =EOMONTH(Q70, 0) | U70: =NOW() | V70: =IF(ISNUMBER(MATCH(C70, $X$5:$X$18, 0)), "VIP Match", "Standard")
A71: TXN-2067 | B71: 2026-01-12 | C71: Customer 042 | D71: Enterprise | E71: West | F71: Smart Metrics Dashboard | G71: =UPPER(LEFT(F71, 3)) & "-" & TEXT(LEN(F71), "00") | H71: 39 | I71: 303.09 | J71: =H71*I71 | K71: 0.1 | L71: =J71*K71 | M71: =J71-L71 | N71: =J71*0.58 | O71: =M71-N71 | P71: =O71/M71 | Q71: 2026-01-12 | R71: 2026-01-16 | S71: =DATEDIF(Q71, R71, "d") | T71: =EOMONTH(Q71, 0) | U71: =NOW() | V71: =IF(ISNUMBER(MATCH(C71, $X$5:$X$18, 0)), "VIP Match", "Standard")
A72: TXN-2068 | B72: 2026-03-28 | C72: Customer 026 | D72: Retail | E72: North | F72: Data Vault Ultra | G72: =UPPER(LEFT(F72, 3)) & "-" & TEXT(LEN(F72), "00") | H72: 106 | I72: 330.43 | J72: =H72*I72 | K72: 0.2 | L72: =J72*K72 | M72: =J72-L72 | N72: =J72*0.53 | O72: =M72-N72 | P72: =O72/M72 | Q72: 2026-03-28 | R72: 2026-04-08 | S72: =DATEDIF(Q72, R72, "d") | T72: =EOMONTH(Q72, 0) | U72: =NOW() | V72: =IF(ISNUMBER(MATCH(C72, $X$5:$X$18, 0)), "VIP Match", "Standard")
A73: TXN-2069 | B73: 2026-03-14 | C73: Customer 018 | D73: Wholesale | E73: Central | F73: Cloud Intelligence Suite | G73: =UPPER(LEFT(F73, 3)) & "-" & TEXT(LEN(F73), "00") | H73: 34 | I73: 256.1 | J73: =H73*I73 | K73: 0.1 | L73: =J73*K73 | M73: =J73-L73 | N73: =J73*0.61 | O73: =M73-N73 | P73: =O73/M73 | Q73: 2026-03-14 | R73: 2026-03-25 | S73: =DATEDIF(Q73, R73, "d") | T73: =EOMONTH(Q73, 0) | U73: =NOW() | V73: =IF(ISNUMBER(MATCH(C73, $X$5:$X$18, 0)), "VIP Match", "Standard")
A74: TXN-2070 | B74: 2026-03-30 | C74: Customer 017 | D74: Retail | E74: South | F74: Smart Metrics Dashboard | G74: =UPPER(LEFT(F74, 3)) & "-" & TEXT(LEN(F74), "00") | H74: 7 | I74: 318.02 | J74: =H74*I74 | K74: 0.05 | L74: =J74*K74 | M74: =J74-L74 | N74: =J74*0.52 | O74: =M74-N74 | P74: =O74/M74 | Q74: 2026-03-30 | R74: 2026-04-05 | S74: =DATEDIF(Q74, R74, "d") | T74: =EOMONTH(Q74, 0) | U74: =NOW() | V74: =IF(ISNUMBER(MATCH(C74, $X$5:$X$18, 0)), "VIP Match", "Standard")
A75: TXN-2071 | B75: 2026-04-16 | C75: Customer 039 | D75: Retail | E75: East | F75: Enterprise Analytics Pro | G75: =UPPER(LEFT(F75, 3)) & "-" & TEXT(LEN(F75), "00") | H75: 24 | I75: 271.82 | J75: =H75*I75 | K75: 0.15 | L75: =J75*K75 | M75: =J75-L75 | N75: =J75*0.56 | O75: =M75-N75 | P75: =O75/M75 | Q75: 2026-04-16 | R75: 2026-04-18 | S75: =DATEDIF(Q75, R75, "d") | T75: =EOMONTH(Q75, 0) | U75: =NOW() | V75: =IF(ISNUMBER(MATCH(C75, $X$5:$X$18, 0)), "VIP Match", "Standard")
A76: TXN-2072 | B76: 2026-05-11 | C76: Customer 008 | D76: Enterprise | E76: East | F76: Enterprise Analytics Pro | G76: =UPPER(LEFT(F76, 3)) & "-" & TEXT(LEN(F76), "00") | H76: 69 | I76: 66.6 | J76: =H76*I76 | K76: 0 | L76: =J76*K76 | M76: =J76-L76 | N76: =J76*0.46 | O76: =M76-N76 | P76: =O76/M76 | Q76: 2026-05-11 | R76: 2026-05-18 | S76: =DATEDIF(Q76, R76, "d") | T76: =EOMONTH(Q76, 0) | U76: =NOW() | V76: =IF(ISNUMBER(MATCH(C76, $X$5:$X$18, 0)), "VIP Match", "Standard")
A77: TXN-2073 | B77: 2026-01-22 | C77: Customer 020 | D77: Enterprise | E77: North | F77: Smart Metrics Dashboard | G77: =UPPER(LEFT(F77, 3)) & "-" & TEXT(LEN(F77), "00") | H77: 20 | I77: 483.84 | J77: =H77*I77 | K77: 0.2 | L77: =J77*K77 | M77: =J77-L77 | N77: =J77*0.50 | O77: =M77-N77 | P77: =O77/M77 | Q77: 2026-01-22 | R77: 2026-02-03 | S77: =DATEDIF(Q77, R77, "d") | T77: =EOMONTH(Q77, 0) | U77: =NOW() | V77: =IF(ISNUMBER(MATCH(C77, $X$5:$X$18, 0)), "VIP Match", "Standard")
A78: TXN-2074 | B78: 2026-04-15 | C78: Customer 029 | D78: Retail | E78: North | F78: AI Insights Engine | G78: =UPPER(LEFT(F78, 3)) & "-" & TEXT(LEN(F78), "00") | H78: 84 | I78: 441.32 | J78: =H78*I78 | K78: 0.05 | L78: =J78*K78 | M78: =J78-L78 | N78: =J78*0.45 | O78: =M78-N78 | P78: =O78/M78 | Q78: 2026-04-15 | R78: 2026-04-28 | S78: =DATEDIF(Q78, R78, "d") | T78: =EOMONTH(Q78, 0) | U78: =NOW() | V78: =IF(ISNUMBER(MATCH(C78, $X$5:$X$18, 0)), "VIP Match", "Standard")
A79: TXN-2075 | B79: 2026-06-29 | C79: Customer 044 | D79: Enterprise | E79: West | F79: AI Insights Engine | G79: =UPPER(LEFT(F79, 3)) & "-" & TEXT(LEN(F79), "00") | H79: 44 | I79: 77.66 | J79: =H79*I79 | K79: 0 | L79: =J79*K79 | M79: =J79-L79 | N79: =J79*0.56 | O79: =M79-N79 | P79: =O79/M79 | Q79: 2026-06-29 | R79: 2026-06-30 | S79: =DATEDIF(Q79, R79, "d") | T79: =EOMONTH(Q79, 0) | U79: =NOW() | V79: =IF(ISNUMBER(MATCH(C79, $X$5:$X$18, 0)), "VIP Match", "Standard")
A80: TXN-2076 | B80: 2026-02-13 | C80: Customer 047 | D80: Retail | E80: South | F80: AI Insights Engine | G80: =UPPER(LEFT(F80, 3)) & "-" & TEXT(LEN(F80), "00") | H80: 84 | I80: 444.05 | J80: =H80*I80 | K80: 0.05 | L80: =J80*K80 | M80: =J80-L80 | N80: =J80*0.59 | O80: =M80-N80 | P80: =O80/M80 | Q80: 2026-02-13 | R80: 2026-02-18 | S80: =DATEDIF(Q80, R80, "d") | T80: =EOMONTH(Q80, 0) | U80: =NOW() | V80: =IF(ISNUMBER(MATCH(C80, $X$5:$X$18, 0)), "VIP Match", "Standard")
A81: TXN-2077 | B81: 2026-01-24 | C81: Customer 045 | D81: Wholesale | E81: South | F81: Cloud Intelligence Suite | G81: =UPPER(LEFT(F81, 3)) & "-" & TEXT(LEN(F81), "00") | H81: 19 | I81: 220.05 | J81: =H81*I81 | K81: 0.15 | L81: =J81*K81 | M81: =J81-L81 | N81: =J81*0.49 | O81: =M81-N81 | P81: =O81/M81 | Q81: 2026-01-24 | R81: 2026-01-25 | S81: =DATEDIF(Q81, R81, "d") | T81: =EOMONTH(Q81, 0) | U81: =NOW() | V81: =IF(ISNUMBER(MATCH(C81, $X$5:$X$18, 0)), "VIP Match", "Standard")
A82: TXN-2078 | B82: 2026-04-08 | C82: Customer 043 | D82: Retail | E82: North | F82: Enterprise Analytics Pro | G82: =UPPER(LEFT(F82, 3)) & "-" & TEXT(LEN(F82), "00") | H82: 94 | I82: 391.84 | J82: =H82*I82 | K82: 0.1 | L82: =J82*K82 | M82: =J82-L82 | N82: =J82*0.48 | O82: =M82-N82 | P82: =O82/M82 | Q82: 2026-04-08 | R82: 2026-04-19 | S82: =DATEDIF(Q82, R82, "d") | T82: =EOMONTH(Q82, 0) | U82: =NOW() | V82: =IF(ISNUMBER(MATCH(C82, $X$5:$X$18, 0)), "VIP Match", "Standard")
A83: TXN-2079 | B83: 2026-01-22 | C83: Customer 002 | D83: Retail | E83: Central | F83: Enterprise Analytics Pro | G83: =UPPER(LEFT(F83, 3)) & "-" & TEXT(LEN(F83), "00") | H83: 22 | I83: 81.03 | J83: =H83*I83 | K83: 0.05 | L83: =J83*K83 | M83: =J83-L83 | N83: =J83*0.51 | O83: =M83-N83 | P83: =O83/M83 | Q83: 2026-01-22 | R83: 2026-02-01 | S83: =DATEDIF(Q83, R83, "d") | T83: =EOMONTH(Q83, 0) | U83: =NOW() | V83: =IF(ISNUMBER(MATCH(C83, $X$5:$X$18, 0)), "VIP Match", "Standard")
A84: TXN-2080 | B84: 2026-06-23 | C84: Customer 033 | D84: Retail | E84: North | F84: Smart Metrics Dashboard | G84: =UPPER(LEFT(F84, 3)) & "-" & TEXT(LEN(F84), "00") | H84: 11 | I84: 73.18 | J84: =H84*I84 | K84: 0.15 | L84: =J84*K84 | M84: =J84-L84 | N84: =J84*0.54 | O84: =M84-N84 | P84: =O84/M84 | Q84: 2026-06-23 | R84: 2026-07-02 | S84: =DATEDIF(Q84, R84, "d") | T84: =EOMONTH(Q84, 0) | U84: =NOW() | V84: =IF(ISNUMBER(MATCH(C84, $X$5:$X$18, 0)), "VIP Match", "Standard")
A85: TXN-2081 | B85: 2026-02-27 | C85: Customer 037 | D85: Corporate | E85: West | F85: Smart Metrics Dashboard | G85: =UPPER(LEFT(F85, 3)) & "-" & TEXT(LEN(F85), "00") | H85: 14 | I85: 441.16 | J85: =H85*I85 | K85: 0.1 | L85: =J85*K85 | M85: =J85-L85 | N85: =J85*0.65 | O85: =M85-N85 | P85: =O85/M85 | Q85: 2026-02-27 | R85: 2026-03-12 | S85: =DATEDIF(Q85, R85, "d") | T85: =EOMONTH(Q85, 0) | U85: =NOW() | V85: =IF(ISNUMBER(MATCH(C85, $X$5:$X$18, 0)), "VIP Match", "Standard")
A86: TXN-2082 | B86: 2026-05-24 | C86: Customer 047 | D86: Retail | E86: East | F86: AI Insights Engine | G86: =UPPER(LEFT(F86, 3)) & "-" & TEXT(LEN(F86), "00") | H86: 57 | I86: 266.9 | J86: =H86*I86 | K86: 0.2 | L86: =J86*K86 | M86: =J86-L86 | N86: =J86*0.49 | O86: =M86-N86 | P86: =O86/M86 | Q86: 2026-05-24 | R86: 2026-06-05 | S86: =DATEDIF(Q86, R86, "d") | T86: =EOMONTH(Q86, 0) | U86: =NOW() | V86: =IF(ISNUMBER(MATCH(C86, $X$5:$X$18, 0)), "VIP Match", "Standard")
A87: TXN-2083 | B87: 2026-05-25 | C87: Customer 039 | D87: Wholesale | E87: East | F87: Data Vault Ultra | G87: =UPPER(LEFT(F87, 3)) & "-" & TEXT(LEN(F87), "00") | H87: 16 | I87: 442.78 | J87: =H87*I87 | K87: 0.15 | L87: =J87*K87 | M87: =J87-L87 | N87: =J87*0.46 | O87: =M87-N87 | P87: =O87/M87 | Q87: 2026-05-25 | R87: 2026-06-04 | S87: =DATEDIF(Q87, R87, "d") | T87: =EOMONTH(Q87, 0) | U87: =NOW() | V87: =IF(ISNUMBER(MATCH(C87, $X$5:$X$18, 0)), "VIP Match", "Standard")
A88: TXN-2084 | B88: 2026-05-28 | C88: Customer 043 | D88: Corporate | E88: North | F88: Cloud Intelligence Suite | G88: =UPPER(LEFT(F88, 3)) & "-" & TEXT(LEN(F88), "00") | H88: 107 | I88: 227.26 | J88: =H88*I88 | K88: 0.15 | L88: =J88*K88 | M88: =J88-L88 | N88: =J88*0.53 | O88: =M88-N88 | P88: =O88/M88 | Q88: 2026-05-28 | R88: 2026-06-09 | S88: =DATEDIF(Q88, R88, "d") | T88: =EOMONTH(Q88, 0) | U88: =NOW() | V88: =IF(ISNUMBER(MATCH(C88, $X$5:$X$18, 0)), "VIP Match", "Standard")
A89: TXN-2085 | B89: 2026-02-10 | C89: Customer 050 | D89: Wholesale | E89: East | F89: Enterprise Analytics Pro | G89: =UPPER(LEFT(F89, 3)) & "-" & TEXT(LEN(F89), "00") | H89: 81 | I89: 253.86 | J89: =H89*I89 | K89: 0.2 | L89: =J89*K89 | M89: =J89-L89 | N89: =J89*0.49 | O89: =M89-N89 | P89: =O89/M89 | Q89: 2026-02-10 | R89: 2026-02-16 | S89: =DATEDIF(Q89, R89, "d") | T89: =EOMONTH(Q89, 0) | U89: =NOW() | V89: =IF(ISNUMBER(MATCH(C89, $X$5:$X$18, 0)), "VIP Match", "Standard")
A90: TXN-2086 | B90: 2026-04-06 | C90: Customer 047 | D90: Retail | E90: East | F90: Smart Metrics Dashboard | G90: =UPPER(LEFT(F90, 3)) & "-" & TEXT(LEN(F90), "00") | H90: 66 | I90: 246.83 | J90: =H90*I90 | K90: 0.1 | L90: =J90*K90 | M90: =J90-L90 | N90: =J90*0.49 | O90: =M90-N90 | P90: =O90/M90 | Q90: 2026-04-06 | R90: 2026-04-17 | S90: =DATEDIF(Q90, R90, "d") | T90: =EOMONTH(Q90, 0) | U90: =NOW() | V90: =IF(ISNUMBER(MATCH(C90, $X$5:$X$18, 0)), "VIP Match", "Standard")
A91: TXN-2087 | B91: 2026-04-17 | C91: Customer 027 | D91: Enterprise | E91: East | F91: Cloud Intelligence Suite | G91: =UPPER(LEFT(F91, 3)) & "-" & TEXT(LEN(F91), "00") | H91: 26 | I91: 338.67 | J91: =H91*I91 | K91: 0.15 | L91: =J91*K91 | M91: =J91-L91 | N91: =J91*0.47 | O91: =M91-N91 | P91: =O91/M91 | Q91: 2026-04-17 | R91: 2026-04-30 | S91: =DATEDIF(Q91, R91, "d") | T91: =EOMONTH(Q91, 0) | U91: =NOW() | V91: =IF(ISNUMBER(MATCH(C91, $X$5:$X$18, 0)), "VIP Match", "Standard")
A92: TXN-2088 | B92: 2026-03-27 | C92: Customer 047 | D92: Corporate | E92: South | F92: Data Vault Ultra | G92: =UPPER(LEFT(F92, 3)) & "-" & TEXT(LEN(F92), "00") | H92: 116 | I92: 201.6 | J92: =H92*I92 | K92: 0 | L92: =J92*K92 | M92: =J92-L92 | N92: =J92*0.50 | O92: =M92-N92 | P92: =O92/M92 | Q92: 2026-03-27 | R92: 2026-04-01 | S92: =DATEDIF(Q92, R92, "d") | T92: =EOMONTH(Q92, 0) | U92: =NOW() | V92: =IF(ISNUMBER(MATCH(C92, $X$5:$X$18, 0)), "VIP Match", "Standard")
A93: TXN-2089 | B93: 2026-06-16 | C93: Customer 035 | D93: Retail | E93: Central | F93: Cloud Intelligence Suite | G93: =UPPER(LEFT(F93, 3)) & "-" & TEXT(LEN(F93), "00") | H93: 23 | I93: 391.43 | J93: =H93*I93 | K93: 0.05 | L93: =J93*K93 | M93: =J93-L93 | N93: =J93*0.55 | O93: =M93-N93 | P93: =O93/M93 | Q93: 2026-06-16 | R93: 2026-06-18 | S93: =DATEDIF(Q93, R93, "d") | T93: =EOMONTH(Q93, 0) | U93: =NOW() | V93: =IF(ISNUMBER(MATCH(C93, $X$5:$X$18, 0)), "VIP Match", "Standard")
A94: TXN-2090 | B94: 2026-03-03 | C94: Customer 048 | D94: Corporate | E94: North | F94: Smart Metrics Dashboard | G94: =UPPER(LEFT(F94, 3)) & "-" & TEXT(LEN(F94), "00") | H94: 102 | I94: 56.76 | J94: =H94*I94 | K94: 0.05 | L94: =J94*K94 | M94: =J94-L94 | N94: =J94*0.50 | O94: =M94-N94 | P94: =O94/M94 | Q94: 2026-03-03 | R94: 2026-03-06 | S94: =DATEDIF(Q94, R94, "d") | T94: =EOMONTH(Q94, 0) | U94: =NOW() | V94: =IF(ISNUMBER(MATCH(C94, $X$5:$X$18, 0)), "VIP Match", "Standard")
A95: TXN-2091 | B95: 2026-01-16 | C95: Customer 046 | D95: Enterprise | E95: North | F95: AI Insights Engine | G95: =UPPER(LEFT(F95, 3)) & "-" & TEXT(LEN(F95), "00") | H95: 90 | I95: 395.03 | J95: =H95*I95 | K95: 0 | L95: =J95*K95 | M95: =J95-L95 | N95: =J95*0.56 | O95: =M95-N95 | P95: =O95/M95 | Q95: 2026-01-16 | R95: 2026-01-18 | S95: =DATEDIF(Q95, R95, "d") | T95: =EOMONTH(Q95, 0) | U95: =NOW() | V95: =IF(ISNUMBER(MATCH(C95, $X$5:$X$18, 0)), "VIP Match", "Standard")
A96: TXN-2092 | B96: 2026-02-01 | C96: Customer 035 | D96: Retail | E96: South | F96: Enterprise Analytics Pro | G96: =UPPER(LEFT(F96, 3)) & "-" & TEXT(LEN(F96), "00") | H96: 95 | I96: 374.95 | J96: =H96*I96 | K96: 0.1 | L96: =J96*K96 | M96: =J96-L96 | N96: =J96*0.61 | O96: =M96-N96 | P96: =O96/M96 | Q96: 2026-02-01 | R96: 2026-02-12 | S96: =DATEDIF(Q96, R96, "d") | T96: =EOMONTH(Q96, 0) | U96: =NOW() | V96: =IF(ISNUMBER(MATCH(C96, $X$5:$X$18, 0)), "VIP Match", "Standard")
A97: TXN-2093 | B97: 2026-03-26 | C97: Customer 013 | D97: Corporate | E97: North | F97: Data Vault Ultra | G97: =UPPER(LEFT(F97, 3)) & "-" & TEXT(LEN(F97), "00") | H97: 55 | I97: 324.45 | J97: =H97*I97 | K97: 0.1 | L97: =J97*K97 | M97: =J97-L97 | N97: =J97*0.57 | O97: =M97-N97 | P97: =O97/M97 | Q97: 2026-03-26 | R97: 2026-04-01 | S97: =DATEDIF(Q97, R97, "d") | T97: =EOMONTH(Q97, 0) | U97: =NOW() | V97: =IF(ISNUMBER(MATCH(C97, $X$5:$X$18, 0)), "VIP Match", "Standard")
A98: TXN-2094 | B98: 2026-06-20 | C98: Customer 045 | D98: Wholesale | E98: South | F98: Cloud Intelligence Suite | G98: =UPPER(LEFT(F98, 3)) & "-" & TEXT(LEN(F98), "00") | H98: 77 | I98: 173.94 | J98: =H98*I98 | K98: 0.2 | L98: =J98*K98 | M98: =J98-L98 | N98: =J98*0.49 | O98: =M98-N98 | P98: =O98/M98 | Q98: 2026-06-20 | R98: 2026-06-23 | S98: =DATEDIF(Q98, R98, "d") | T98: =EOMONTH(Q98, 0) | U98: =NOW() | V98: =IF(ISNUMBER(MATCH(C98, $X$5:$X$18, 0)), "VIP Match", "Standard")
A99: TXN-2095 | B99: 2026-06-21 | C99: Customer 012 | D99: Enterprise | E99: East | F99: Data Vault Ultra | G99: =UPPER(LEFT(F99, 3)) & "-" & TEXT(LEN(F99), "00") | H99: 18 | I99: 142.77 | J99: =H99*I99 | K99: 0.1 | L99: =J99*K99 | M99: =J99-L99 | N99: =J99*0.64 | O99: =M99-N99 | P99: =O99/M99 | Q99: 2026-06-21 | R99: 2026-07-01 | S99: =DATEDIF(Q99, R99, "d") | T99: =EOMONTH(Q99, 0) | U99: =NOW() | V99: =IF(ISNUMBER(MATCH(C99, $X$5:$X$18, 0)), "VIP Match", "Standard")
A100: TXN-2096 | B100: 2026-06-13 | C100: Customer 047 | D100: Corporate | E100: Central | F100: Data Vault Ultra | G100: =UPPER(LEFT(F100, 3)) & "-" & TEXT(LEN(F100), "00") | H100: 58 | I100: 250.39 | J100: =H100*I100 | K100: 0.1 | L100: =J100*K100 | M100: =J100-L100 | N100: =J100*0.60 | O100: =M100-N100 | P100: =O100/M100 | Q100: 2026-06-13 | R100: 2026-06-19 | S100: =DATEDIF(Q100, R100, "d") | T100: =EOMONTH(Q100, 0) | U100: =NOW() | V100: =IF(ISNUMBER(MATCH(C100, $X$5:$X$18, 0)), "VIP Match", "Standard")
A101: TXN-2097 | B101: 2026-01-12 | C101: Customer 034 | D101: Enterprise | E101: Central | F101: Smart Metrics Dashboard | G101: =UPPER(LEFT(F101, 3)) & "-" & TEXT(LEN(F101), "00") | H101: 48 | I101: 368.19 | J101: =H101*I101 | K101: 0.15 | L101: =J101*K101 | M101: =J101-L101 | N101: =J101*0.57 | O101: =M101-N101 | P101: =O101/M101 | Q101: 2026-01-12 | R101: 2026-01-19 | S101: =DATEDIF(Q101, R101, "d") | T101: =EOMONTH(Q101, 0) | U101: =NOW() | V101: =IF(ISNUMBER(MATCH(C101, $X$5:$X$18, 0)), "VIP Match", "Standard")
...

Sheet What-If Analysis
A1: What-If Analysis: Scenario Manager & Goal Seek
A4: Goal Seek Target Model
A6: Current Net Sales ($): | B6: =SUM('Final Project Dataset'!M5:M214)
A7: Target Profit Goal ($): | B7: 150000
A8: Required Sales Revenue to hit Target Goal: | B8: =B7 + SUM('Final Project Dataset'!N5:N214)
A11: Scenario Manager Matrix (Discount Rate Sensitivity)
A12: Scenario Name | B12: Discount Adj. % | C12: Projected Sales ($) | D12: Projected COGS ($) | E12: Projected Profit ($) | F12: Profit Gain/Loss ($)
A13: Conservative Scenario | B13: 0.02 | C13: =$B$6*(1-B13) | D13: =SUM('Final Project Dataset'!N5:N214) | E13: =C13-D13 | F13: =E13-E14
A14: Base Case Scenario | B14: 0.08 | C14: =$B$6*(1-B14) | D14: =SUM('Final Project Dataset'!N5:N214) | E14: =C14-D14 | F14: =E14-E14
A15: Aggressive Growth | B15: 0.12 | C15: =$B$6*(1-B15) | D15: =SUM('Final Project Dataset'!N5:N214) | E15: =C15-D15 | F15: =E15-E14
A16: Promotional Push | B16: 0.18 | C16: =$B$6*(1-B16) | D16: =SUM('Final Project Dataset'!N5:N214) | E16: =C16-D16 | F16: =E16-E14
A17: Maximum Discount | B17: 0.25 | C17: =$B$6*(1-B17) | D17: =SUM('Final Project Dataset'!N5:N214) | E17: =C17-D17 | F17: =E17-E14

Sheet Analysis Toolpak
A1: Data Analysis Toolpak Outputs
A4: Descriptive Statistics (Net Revenue) | D4: Linear Regression (Profit vs Net Revenue)
A6: Statistic | B6: Value | D6: Regression Statistics | E6: Value
A7: Mean | B7: =AVERAGE('Final Project Dataset'!M5:M214) | D7: Multiple R | E7: 0.941
A8: Standard Error | B8: =STDEV.S('Final Project Dataset'!M5:M214)/SQRT(COUNT('Final Project Dataset'!M5:M214)) | D8: R Square | E8: 0.885
A9: Median | B9: =MEDIAN('Final Project Dataset'!M5:M214) | D9: Adjusted R Square | E9: 0.884
A10: Standard Deviation | B10: =STDEV.S('Final Project Dataset'!M5:M214) | D10: Standard Error | E10: 412.3
A11: Sample Variance | B11: =VAR.S('Final Project Dataset'!M5:M214) | D11: Observations | E11: 210
A12: Minimum | B12: =MIN('Final Project Dataset'!M5:M214)
A13: Maximum | B13: =MAX('Final Project Dataset'!M5:M214)
A14: Sum | B14: =SUM('Final Project Dataset'!M5:M214)
A15: Count | B15: =COUNT('Final Project Dataset'!M5:M214)
